folktexts/__init__.py
folktexts/_io.py
folktexts/_utils.py
folktexts/_version.py
folktexts/benchmark.py
folktexts/col_to_text.py
folktexts/dataset.py
folktexts/evaluation.py
folktexts/llm_utils.py
folktexts/plotting.py
folktexts/prompting.py
folktexts/qa_interface.py
folktexts/task.py
folktexts/threshold.py
folktexts/acs/__init__.py
folktexts/acs/_utils.py
folktexts/acs/acs_columns.py
folktexts/acs/acs_dataset.py
folktexts/acs/acs_questions.py
folktexts/acs/acs_tasks.py
folktexts/acs/acs_thresholds.py
folktexts/acs/data/ANC1P.txt
folktexts/acs/data/HISP.txt
folktexts/acs/data/LANP.txt
folktexts/acs/data/OCCP.txt
folktexts/acs/data/POBP.txt
folktexts/acs/data/ST.txt
folktexts/classifier/__init__.py
folktexts/classifier/base.py
folktexts/classifier/transformers_classifier.py
folktexts/classifier/web_api_classifier.py
folktexts/cli/__init__.py
folktexts/cli/_utils.py
folktexts/cli/download_models.py
folktexts/cli/eval_feature_importance.py
folktexts/cli/experiments.py
folktexts/cli/launch_experiments_htcondor.py
folktexts/cli/rerun_experiment.py
folktexts/cli/run_acs_benchmark.py
folktexts-0.1.1.dist-info/licenses/LICENSE
folktexts-0.1.1.dist-info/METADATA
folktexts-0.1.1.dist-info/WHEEL
folktexts-0.1.1.dist-info/entry_points.txt
folktexts-0.1.1.dist-info/top_level.txt
folktexts-0.1.1.dist-info/RECORD
