Metadata-Version: 2.4
Name: folktexts
Version: 0.1.1
Summary: Use LLMs to get classification risk scores on tabular tasks.
Author: Andre Cruz, Ricardo Dominguez-Olmedo, Celestine Mendler-Dunner, Moritz Hardt
License: MIT License
Project-URL: homepage, https://github.com/socialfoundations/folktexts
Project-URL: repository, https://github.com/socialfoundations/folktexts
Project-URL: documentation, https://socialfoundations.github.io/folktexts/
Keywords: language-model,risk-estimation,benchmark,machine-learning
Classifier: Development Status :: 3 - Alpha
Classifier: License :: OSI Approved :: MIT License
Classifier: Intended Audience :: Science/Research
Classifier: Topic :: Scientific/Engineering :: Artificial Intelligence
Classifier: Natural Language :: English
Classifier: Programming Language :: Python :: 3
Classifier: Programming Language :: Python :: 3.8
Classifier: Programming Language :: Python :: 3.9
Classifier: Programming Language :: Python :: 3.10
Classifier: Programming Language :: Python :: 3.11
Classifier: Programming Language :: Python :: 3.12
Requires-Python: >=3.8
License-File: LICENSE
Requires-Dist: folktables~=0.0.12
Requires-Dist: scikit-learn>=1.3
Requires-Dist: numpy
Requires-Dist: pandas
Requires-Dist: tqdm
Requires-Dist: accelerate
Requires-Dist: transformers>=4.42.4
Requires-Dist: torch
Requires-Dist: sentencepiece
Requires-Dist: protobuf
Requires-Dist: netcal
Requires-Dist: cloudpickle
Requires-Dist: matplotlib
Requires-Dist: seaborn
Provides-Extra: tests
Requires-Dist: pytest; extra == "tests"
Requires-Dist: coverage; extra == "tests"
Requires-Dist: flake8-pyproject; extra == "tests"
Requires-Dist: flake8; extra == "tests"
Requires-Dist: mypy; extra == "tests"
Requires-Dist: tox; extra == "tests"
Provides-Extra: docs
Requires-Dist: sphinx<8,>=6; extra == "docs"
Requires-Dist: sphinx_rtd_theme>=2.0; extra == "docs"
Requires-Dist: sphinx-autopackagesummary; extra == "docs"
Requires-Dist: myst-parser; extra == "docs"
Requires-Dist: sphinx-copybutton; extra == "docs"
Requires-Dist: sphinxcontrib-bibtex; extra == "docs"
Requires-Dist: sphinxemoji; extra == "docs"
Requires-Dist: sphinx-autodoc-typehints; extra == "docs"
Requires-Dist: numpydoc; extra == "docs"
Requires-Dist: nbsphinx; extra == "docs"
Requires-Dist: sphinx_gallery; extra == "docs"
Requires-Dist: IPython; extra == "docs"
Requires-Dist: ipykernel; extra == "docs"
Provides-Extra: cluster
Requires-Dist: htcondor; extra == "cluster"
Requires-Dist: xgboost; extra == "cluster"
Provides-Extra: apis
Requires-Dist: litellm>=1.40.14; extra == "apis"
Requires-Dist: openai>=1.1.0; extra == "apis"
Dynamic: license-file
